AFEX_SSO/__init__.py
AFEX_SSO/src/__init__.py
AFEX_SSO/src/get_hash_key.py
AFEX_SSO/src/sso.py
AFEX_SSO/src/views.py
afex_sso-0.0.62.dist-info/LICENSE
afex_sso-0.0.62.dist-info/METADATA
afex_sso-0.0.62.dist-info/WHEEL
afex_sso-0.0.62.dist-info/top_level.txt
afex_sso-0.0.62.dist-info/RECORD
