Metadata-Version: 2.1
Name: afex-sso
Version: 0.0.62
Summary: For integrating sso
Home-page: UNKNOWN
Author: AFEX NIGERIA
Author-email: it@africaexchange.com
License: MIT
Platform: UNKNOWN
Classifier: License :: OSI Approved :: MIT License
Classifier: Programming Language :: Python :: 3.8
Classifier: Operating System :: OS Independent
Requires-Python: >=3.7
Requires-Dist: requests (>=2.28.2)
Requires-Dist: django (>=3.2)
Provides-Extra: dev
Requires-Dist: pytest (>=7.0) ; extra == 'dev'
Requires-Dist: twine (>=4.0.2) ; extra == 'dev'
